fastapi_query/__init__.py
fastapi_query/_compat.py
fastapi_query/ext/__init__.py
fastapi_query/ext/sqlalchemy/__init__.py
fastapi_query/ext/sqlalchemy/filtering.py
fastapi_query/ext/sqlalchemy/ordering.py
fastapi_query/ext/sqlalchemy/pagination.py
fastapi_query/ext/tortoise/__init__.py
fastapi_query/ext/tortoise/filtering.py
fastapi_query/ext/tortoise/ordering.py
fastapi_query/ext/tortoise/pagination.py
fastapi_query/ext/tortoise/utils.py
fastapi_query/filtering/__init__.py
fastapi_query/filtering/base_params.py
fastapi_query/filtering/deps.py
fastapi_query/filtering/enums.py
fastapi_query/filtering/utils.py
fastapi_query/pagination/__init__.py
fastapi_query/pagination/deps.py
fastapi_query/pagination/schemas.py
fastapi_query/pagination/utils.py
fastapi_query/utils.py
fastapi_query-0.1a0.dist-info/LICENSE
fastapi_query-0.1a0.dist-info/METADATA
fastapi_query-0.1a0.dist-info/WHEEL
fastapi_query-0.1a0.dist-info/RECORD
